oathkeeper
