Metadata-Version: 2.1
Name: oathkeeper
Version: 0.0.7
Summary: Oathkeeper Package
Home-page: https://github.com/greendeck
Author: yashvardhan srivastava
Author-email: yash@greendeck.com
License: UNKNOWN
Platform: UNKNOWN
Classifier: Programming Language :: Python :: 3
Classifier: License :: OSI Approved :: MIT License
Classifier: Operating System :: OS Independent
